{
  "project_info": {
    "project_number": "385747325165",
    "project_id": "crickyworld-effd1",
    "storage_bucket": "crickyworld-effd1.firebasestorage.app"
  },
  "client": [
    {
      "client_info": {
        "mobilesdk_app_id": "1:385747325165:android:6d92c011cbed06bbd2bce4",
        "android_client_info": {
          "package_name": "com.crickyworld"
        }
      },
      "oauth_client": [],
      "api_key": [
        {
          "current_key": "AIzaSyB--c3O0nfLoVzlMS9tthzfW8BsqOGVCeo"
        }
      ],
      "services": {
        "appinvite_service": {
          "other_platform_oauth_client": []
        }
      }
    }
  ],
  "configuration_version": "1"
}